formflow/__init__.py
formflow/eslint.config.js
formflow/index.html
formflow/package-lock.json
formflow/package.json
formflow/privacy-policy.md
formflow/tsconfig.app.json
formflow/tsconfig.json
formflow/tsconfig.node.json
formflow/vite.config.ts
formflow/dist/contact-us.webp
formflow/dist/index.html
formflow/dist/styles.css
formflow/dist/assets/index-CLbeYbjT.js
formflow/dist/assets/index-CQOsgyPg.css
formflow/src/App.tsx
formflow/src/AuthContext.tsx
formflow/src/Footer.tsx
formflow/src/Header.tsx
formflow/src/Layout.tsx
formflow/src/Navigation.tsx
formflow/src/global.css
formflow/src/global.d.ts
formflow/src/html.d.ts
formflow/src/main.tsx
formflow/src/utils.ts
formflow/src/vite-env.d.ts
formflow/src/components/PrivateRoute.tsx
formflow/src/components/PublicRoute.tsx
formflow/src/pages/Account.tsx
formflow/src/pages/CheckEmail.tsx
formflow/src/pages/ContactUs.tsx
formflow/src/pages/HowItWorks.tsx
formflow/src/pages/LandingPage.css
formflow/src/pages/LandingPage.tsx
formflow/src/pages/PrivacyPolicy.tsx
formflow/src/pages/SignIn.tsx
formflow/src/pages/SignUp.tsx
formflow/src/pages/SignedIn.tsx
formflow-1.0.27.dist-info/METADATA
formflow-1.0.27.dist-info/WHEEL
formflow-1.0.27.dist-info/entry_points.txt
formflow-1.0.27.dist-info/licenses/LICENSE
formflow-1.0.27.dist-info/RECORD
