Metadata-Version: 2.4
Name: formflow
Version: 1.0.27
Summary: FormFlow allows easy 'Contact Us' form integration.
Project-URL: Homepage, https://github.com/mizuki-hikaru/formflow
Project-URL: Issues, https://github.com/mizuki-hikaru/formflow/issues
Author-email: Mizuki Hikaru <mizuki@hikaru.org>
License-File: LICENSE
Classifier: License :: OSI Approved :: MIT License
Classifier: Operating System :: OS Independent
Classifier: Programming Language :: Python :: 3
Requires-Python: >=3.9
Requires-Dist: authbase
Requires-Dist: fastapi[standard]
